{
  "version": "1.0.0",
  "events": [
    {
      "id": "AP02E001",
      "type": "personal",
      "title": "白芷·R1·采药购装",
      "participants": ["P02"],
      "priority": 10,
      "once": true,
      "trigger": {
        "requirements": [],
        "conditions": [
          { "scope": "world", "attr": "round", "op": ">=", "value": 1 }
        ]
      },
      "outcomes": [
        {
          "id": "AP02E001O001",
          "priority": 100,
          "conditions": [],
          "text": "铺子刚开门不久，一个背着药篓的少女走了进来。她手指被药汁染得发绿，道袍袖口有几处烧焦的小洞——白芷，药王谷的炼丹弟子。她在货架前站定，目光从一排法宝上扫过，嘴里嘟囔着：'这个成色不行……那个火候过了……'她不是在挑剔，只是在做药材鉴定做惯了。最后她选了一件适合在林间穿行的装备，付了灵石，把东西往药篓里一塞，朝掌柜点了点头：'多谢。我去城外那片老林子里采几味药，回头再来。'",
          "next": [
            { "target": "P02", "nextId": "AP02E002" }
          ]
        }
      ]
    },
    {
      "id": "AP02E002",
      "type": "personal",
      "title": "白芷·R2·采药归来",
      "participants": ["P02"],
      "priority": 10,
      "once": true,
      "trigger": {
        "requirements": [],
        "conditions": [
          { "scope": "world", "attr": "round", "op": ">=", "value": 2 }
        ]
      },
      "outcomes": [
        {
          "id": "AP02E002O001",
          "priority": 100,
          "conditions": [
            { "scope": "npc", "target": "P02", "attr": "speed", "op": ">=", "value": 7 }
          ],
          "text": "白芷推门进来的时候，脸上带着藏不住的笑。药篓里多了几株还带着露水的灵草，根茎完整，品相极好——林子里那几处陡坡没难住她，靠的就是上回在这儿买的装备。她从袖子里摸出十块下品灵石，整整齐齐码在柜台上：'掌柜的，这是谢礼。要不是你卖给我的东西好使，那片老林子深处我根本进不去。'说着她又扫了一眼货架，目光比上次认真了许多。城南遗迹的消息她已经听说了，里面可能有上古灵药——如果能采到一两株，带回药王谷就够资格参加炼丹考核。她把自己的灵石袋翻了个底朝天：'遗迹里的禁制不是闹着玩的，掌柜的，有什么能保命的好东西？'",
          "next": [
            { "target": "P02", "nextId": "AP02E003" }
          ]
        },
        {
          "id": "AP02E002O002",
          "priority": 1,
          "conditions": [],
          "text": "白芷推门进来的时候，袖口沾着泥，头发上挂了两片枯叶子，药篓里空空荡荡。林子里那片陡坡太滑了——她在坡底坐了一会儿，看着头顶的灵草够不着，叹了口气就回来了。但她没在这件事上纠结太久。城南遗迹的消息已经传遍了半座城，她的心思全转到了那里：上古修士的洞府里，说不定能采到一两株失传的灵药。她把灵石袋翻了个底朝天，咬咬牙：'掌柜的，遗迹里的禁制不是闹着玩的。有什么能保命的东西，给我看看。'",
          "next": [
            { "target": "P02", "nextId": "AP02E003" }
          ]
        }
      ]
    },
    {
      "id": "AP02E003",
      "type": "personal",
      "title": "白芷·R3·遗迹结果",
      "participants": ["P02"],
      "priority": 10,
      "once": true,
      "trigger": {
        "requirements": [],
        "conditions": [
          { "scope": "world", "attr": "round", "op": ">=", "value": 3 }
        ]
      },
      "outcomes": [
        {
          "id": "AP02E003O001",
          "priority": 100,
          "conditions": [
            { "scope": "npc", "target": "P02", "attr": "attack", "op": ">=", "value": 7 },
            { "scope": "npc", "target": "P02", "attr": "defense", "op": ">=", "value": 5 },
            { "scope": "npc", "target": "P02", "attr": "speed", "op": ">=", "value": 7 }
          ],
          "text": "几天过去，白芷没有回来。铺子里的日子照常过，南坊散修们的话题已经从遗迹转到了'谁又死在里面了'。但掌柜心里有数——那姑娘走的时候装备齐整，身上带的丹药也够。她只是在遗迹深处多待了一些时日。上古灵药不会长在入口处，好东西总是要往深处走的。",
          "next": [
            { "target": "P02", "nextId": "AP02E004" }
          ]
        },
        {
          "id": "AP02E003O002",
          "priority": 1,
          "conditions": [],
          "text": "白芷回来的比预想的快得多。她推门进来的时候脸色不太好，道袍上多了两道被禁制划开的口子，左手腕缠着一截临时撕下来的布条——渗着淡淡的血。'遗迹里的禁制比我想的凶。'她没有拐弯抹角，直接走到柜台前，'我一个人进不到核心区。但我发现了一条路，只要有个能打的在前面开路……'她顿了一下，像是在斟酌措辞，'掌柜的，你这里往来的散修多，有没有人——剑用得好的那种——也在找遗迹里的东西？'",
          "next": [
            { "target": "P02", "nextId": "AP02E019" }
          ]
        }
      ]
    },
    {
      "id": "C001",
      "type": "common",
      "title": "遗迹·双人探索",
      "participants": ["P01", "P02"],
      "priority": 80,
      "once": true,
      "trigger": {
        "requirements": [
          { "target": "P01", "eventId": "AP01E002" },
          { "target": "P02", "eventId": "AP02E019" }
        ],
        "conditions": [
          { "scope": "world", "attr": "round", "op": ">=", "value": 4 }
        ]
      },
      "outcomes": [
        {
          "id": "C001O001",
          "priority": 100,
          "conditions": [
            { "scope": "npc", "target": "P01", "attr": "attack", "op": ">=", "value": 7 },
            { "scope": "npc", "target": "P02", "attr": "attack", "op": ">=", "value": 6 },
            { "scope": "npc", "target": "P02", "attr": "defense", "op": ">=", "value": 5 }
          ],
          "text": "白芷从铺子里带回来的帮手比她想象中靠谱。那个腰挂断剑的少年话不多，但他的剑太快了——遗迹里那道把白芷拦在外围的禁制，在他剑下撑了不到一炷香。白芷跟在后面，靠丹药和防御法宝稳住了两人的状态，一路上她采到了三株至少千年份的灵药。走出遗迹的时候，白芷回头看了一眼——那个用剑的少年站在废墟里，似乎在感应什么更深处的东西。她没打扰他，只是把一株多余的灵药留在了旁边的石头上，用一张丹方垫着——上面写了配比和火候，对剑修疗伤有奇效。然后她一个人往南坊的方向走去。药篓很重，但她的脚步很轻。有些事情要在第六回合才会说出口，但现在她已经知道——这趟遗迹，来对了。",
          "next": [
            { "target": "P01", "nextId": "AP01E013" },
            { "target": "P02", "nextId": "AP02E009" }
          ]
        },
        {
          "id": "C001O002",
          "priority": 1,
          "conditions": [],
          "text": "白芷和那个用断剑的少年一起进了遗迹。两天后两人从城南方向走出来——灰头土脸，但都活着。那道禁制最终没能破开——少年在前面劈了三剑，一剑比一剑弱；白芷的护体丹也用尽了，再往深处两人的状态都扛不住。在南坊路口，少年攥紧剑柄往北坊走了，白芷往城门口的方向走。药篓还是空的。灵药采不到，丹方残页就只能继续锁在暗格里。赵元恪的倒计时——还没开始。",
          "next": [
            { "target": "P01", "nextId": "EVENT_INACTIVE" },
            { "target": "P02", "nextId": "EVENT_INACTIVE" }
          ]
        }
      ]
    },
    {
      "id": "AP02E004",
      "type": "personal",
      "title": "白芷·A线·R6·功成回谷",
      "participants": ["P02"],
      "priority": 10,
      "once": true,
      "trigger": {
        "requirements": [],
        "conditions": [
          { "scope": "world", "attr": "round", "op": ">=", "value": 6 }
        ]
      },
      "outcomes": [
        {
          "id": "AP02E004O001",
          "priority": 100,
          "conditions": [],
          "text": "白芷推门进来的时候，掌柜差点没认出她。那个手指发绿的少女变化不大——药篓还在背上，袖子上的焦洞还是那几个——但她的眼神变了。不是变凌厉了，是变沉了。她从药篓底层小心翼翼地捧出一个玉盒，打开一条缝，一股清冽的药香瞬间弥漫开来，整个铺子的空气都凉了几度。'上古灵药——至少三千年份的玄霜草。'她的声音很轻，像怕惊动什么，'够我回药王谷参加考核了。'她合上玉盒，重新包好，然后抬起头看着掌柜，认真地说：'谢谢你。这两次来你铺子，买的装备都救了我的命。'她从袖子里摸出一块小玉牌放在柜台上，刻着药王谷的丹炉纹样，又从药篓里掏出一个小瓷瓶——几粒她自己炼的养气丹。'玉牌是信物。丹药是我自己炼的——比不上铺子里的好，但栽在花盆里能治灵植。以后来谷里找我。'说完背好药篓，走出了铺子。南坊的阳光照在她身上，那道被禁制划破的旧口子还挂在袖口——但人已经不是来时的那个人了。",
          "next": [
            { "target": "P02", "nextId": "AP02E005" }
          ]
        }
      ]
    },
    {
      "id": "AP02E005",
      "type": "personal",
      "title": "白芷·A线·R10·考核补料",
      "participants": ["P02"],
      "priority": 10,
      "once": true,
      "trigger": {
        "requirements": [],
        "conditions": [
          { "scope": "world", "attr": "round", "op": ">=", "value": 10 }
        ]
      },
      "outcomes": [
        {
          "id": "AP02E005O001",
          "priority": 100,
          "conditions": [],
          "text": "白芷推开铺子门的时候，掌柜注意到她袖口的焦洞多了几个——不是失败，是炼了太多炉。她把玄霜草在谷里的丹房炼了一炉——丹成那晚，丹炉盖弹开的时候，炉口涌出的药气让隔壁丹房的两个师兄跑了过来，以为出了事故。不是事故——是三千年的灵药在说话。她在货架上仔细挑了几味辅料类灵植，都是低年份的，但品相要求极严。她不是买不到，是在铺子里挑习惯了。'掌柜的，这些够了。'她把灵石袋放在柜台上——比上次来时多了些灵石。'我这次回去要参加内门考核。如果过了——我就能进内门藏书阁。那里有全谷最老的档案。'她看着掌柜，没有解释'老档案'意味着什么。但掌柜记得她第一次来时手指上那些被药汁染绿的痕迹——一个翻档案翻到手指发绿的人，不会无缘无故提老档案。",
          "next": [
            { "target": "P02", "nextId": "AP02E006" }
          ]
        }
      ]
    },
    {
      "id": "AP02E006",
      "type": "personal",
      "title": "白芷·A线·R13·接近内门搜证",
      "participants": ["P02"],
      "priority": 10,
      "once": true,
      "trigger": {
        "requirements": [],
        "conditions": [
          { "scope": "world", "attr": "round", "op": ">=", "value": 13 }
        ]
      },
      "outcomes": [
        {
          "id": "AP02E006O001",
          "priority": 100,
          "conditions": [
            { "scope": "npc", "target": "P02", "attr": "defense", "op": ">=", "value": 7 }
          ],
          "text": "白芷再次推开铺子门的时候，道袍换了一件新的——不是料子好，是旧的已经补不上了。袖口依然有焦洞，但手指上多了几道细小的烫痕——炼制高品级丹药时丹炉反噬留下的。'掌柜的，我需要几颗护体丹——不是进遗迹那种，是在谷里用的，要能抗住炼丹失败时的炉火反噬。'她选了几颗品相最好的护体丹，又问了一句让掌柜觉得她话里有话的话：'有没有那种——能防神识探查的法宝？哪怕是凡品的也行。'她不是在开玩笑。药王谷内门藏书阁的通行令牌让她能接触到更老的档案——而她已经翻到了第二十三年前后的入库记录。有一页被人撕掉了。撕得很整齐——不是意外破损，是拿尺子比着裁的。她花了两个季度逐页核对入库记录和残页上的墨迹，终于锁定了撕掉那页的人——入库记录上最后一个签字的管理弟子，现在已经是赵元恪的贴身丹童。她把这些证据锁进了独立丹房的暗格里——不是玉牌信物那种公开的东西，是一份完整的线索链。",
          "next": [
            { "target": "P02", "nextId": "AP02E007" }
          ]
        },
        {
          "id": "AP02E006O002",
          "priority": 1,
          "conditions": [],
          "text": "白芷再次推开铺子门，买了几颗护体丹。但防神识探查的法宝——铺子里没有。她翻档案的动作被注意到了。不是赵元恪本人——是他一个在藏书阁当值的学生。那个学生没说什么，只是某天在走廊里'碰巧'遇到了白芷，笑着问了一句：'师妹最近对旧档案很感兴趣？'白芷笑着说'考核要用'。但那天之后，她去藏书阁的时间从白天改到了下半夜。",
          "next": [
            { "target": "P02", "nextId": "AP02E007" }
          ]
        }
      ]
    },
    {
      "id": "AP02E007",
      "type": "personal",
      "title": "白芷·A线·R20·揭发赵元恪",
      "participants": ["P02"],
      "priority": 10,
      "once": true,
      "trigger": {
        "requirements": [],
        "conditions": [
          { "scope": "world", "attr": "round", "op": ">=", "value": 20 }
        ]
      },
      "outcomes": [
        {
          "id": "AP02E007O001",
          "priority": 100,
          "conditions": [
            { "scope": "npc", "target": "P02", "attr": "defense", "op": ">=", "value": 7 }
          ],
          "text": "天剑宗改革成功的消息传到玄清宗，长老会连夜开会。同一时间，一个退居二线的老丹师在整理旧档时翻到了柳玄清二十三年前一份未被销毁的原始日志——那行被涂改的辅料清单背面，凹痕还在：'赤硝，三钱'。老丹师拿着日志，白芷拿着丹方残页原件，连同柳玄清被囚的证据，一并递到了执法堂。三份证据互相印证——不需要外部人证，物证本身已经构成闭环。天剑宗的外部压力让长老会没人敢压这件事。赵元恪在执法堂上当面对质时笑了——不是镇定，是知道完了。他最后问了一句话：'你一个外门弟子，翻档案翻了几年？'白芷没有回答。她只是把丹方残页放在桌上，那行'九转时加三钱赤硝'正对着执法堂长老的眼睛。师父获救倒计时：立即。",
          "next": [
            { "target": "P02", "nextId": "AP02E008" }
          ]
        },
        {
          "id": "AP02E007O002",
          "priority": 50,
          "conditions": [
            { "scope": "npc", "target": "P02", "attr": "defense", "op": ">=", "value": 5 }
          ],
          "text": "天剑宗改革的外部压力仍在，但物证链不够完整——防神识法宝没买到，搜证时被注意到了，原件的一部分被赵元恪提前销毁。老丹师的日志和白芷的残页抄本互相印证，但关键原件不全。天剑宗改革的示范效应让玄清宗启动了内部调查——慢，但已经在动了。赵元恪被暂停职务三个月，够他销毁剩余证据，但风声已经走漏。师父获救倒计时：延期但未取消。",
          "next": [
            { "target": "P02", "nextId": "AP02E008" }
          ]
        },
        {
          "id": "AP02E007O003",
          "priority": 1,
          "conditions": [],
          "text": "玄清宗内部调查被启动，但白芷手里的证据散落且薄弱——只有抄本没有原件。调查进展缓慢，赵元恪在调查期间逐步销毁关键痕迹。但调查本身就是一个信号——他不再高枕无忧了。师父获救倒计时：大幅推迟。",
          "next": [
            { "target": "P02", "nextId": "AP02E008" }
          ]
        }
      ]
    },
    {
      "id": "AP02E008",
      "type": "personal",
      "title": "白芷·A线·R26·终局回访",
      "participants": ["P02"],
      "priority": 10,
      "once": true,
      "trigger": {
        "requirements": [],
        "conditions": [
          { "scope": "world", "attr": "round", "op": ">=", "value": 26 }
        ]
      },
      "outcomes": [
        {
          "id": "AP02E008O001",
          "priority": 100,
          "conditions": [],
          "text": "白芷推开了南坊铺子的门。她穿着内门弟子的新道袍——袖口依然有焦洞，手指依然发绿。有些东西不会变。她在柜台前站了一会儿，然后把一个玉盒放在柜台上。不是三千年份的玄霜草——是一盒她自己炼的丹药。每一颗都贴着标签，写了配比、火候、服用禁忌。字迹工整——和丹方残页上那种旧式写法一模一样，只是新的。'掌柜的。二十三年前有人用一张丹方害了一个人。二十三年后——我用这些补上。不是还给谁，是放在你这儿——以后有人要，就给他们。'她鞠了一躬——不是外门弟子对长老那种，是一个炼丹的人对另一个帮过她的人。走到门口时停了一下，回过头：'那间四人合用的丹房——我已经搬出来了。新丹房的暗格里，还锁着那页残页的原件。赵元恪的事结了——但那页纸，我会一直留着。'南坊的阳光很好。她背好药篓——那个旧药篓，背了这么多年还没换——走进了人群里。太阳照在她袖口的焦洞上，像是二十三年前那场炸炉的火光，终于在漫长的时间里冷了下去。",
          "next": [
            { "target": "P02", "nextId": "EVENT_INACTIVE" }
          ]
        }
      ]
    },
    {
      "id": "AP02E009",
      "type": "personal",
      "title": "白芷·B1线·R6·组队回谷",
      "participants": ["P02"],
      "priority": 10,
      "once": true,
      "trigger": {
        "requirements": [],
        "conditions": [
          { "scope": "world", "attr": "round", "op": ">=", "value": 6 }
        ]
      },
      "outcomes": [
        {
          "id": "AP02E009O001",
          "priority": 100,
          "conditions": [
            { "scope": "npc", "target": "P02", "attr": "defense", "op": ">=", "value": 6 },
            { "scope": "npc", "target": "P02", "attr": "speed", "op": ">=", "value": 6 }
          ],
          "text": "白芷推开铺子的门。道袍上新添了一道口子——就是当初那道禁制留下的——但她的神色比独自来的时候多了几分沉稳。她不光靠自己活了下来，还帮了另一个人。她从背后拿出在遗迹里采到的几株千年灵药——品质不差，但数量和年份都不如独自深入核心时采到的。在她身后，那个用断剑的少年已经消失在巷子尽头。她把灵药摊开给掌柜看：'我在双人探索中是跟在后面的辅助角色——采药的时间和范围都被压缩了。但这些够我回谷了。'她从袖子里摸出一块小玉牌放在柜台上，又从药篓里掏出一小包灵植种子：'掌柜的，这些种子是遗迹里采的——不是上古灵药，是外围岩缝里长的。但药性很稳，种在院子里能当炼丹辅料。'这不是信物，是种子——是'以后还会长东西'的意思。",
          "next": [
            { "target": "P02", "nextId": "AP02E010" }
          ]
        },
        {
          "id": "AP02E009O002",
          "priority": 1,
          "conditions": [],
          "text": "白芷推开铺子的门。道袍上新添了一道口子，但她的神色比独自失败时多了几分沉稳。她把从遗迹里采到的几株灵药摊在柜台上——不多，但够回谷用了。她把一块小玉牌留下：'掌柜的，借你的装备保住了一条命。剩下的事——回谷再说。'说完背好药篓走了。她没有多说什么，但她知道——那个用断剑的少年还活着，会记住她留在石头上的那张丹方。",
          "next": [
            { "target": "P02", "nextId": "AP02E010" }
          ]
        }
      ]
    },
    {
      "id": "AP02E010",
      "type": "personal",
      "title": "白芷·B1线·R10·考核边缘",
      "participants": ["P02"],
      "priority": 10,
      "once": true,
      "trigger": {
        "requirements": [],
        "conditions": [
          { "scope": "world", "attr": "round", "op": ">=", "value": 10 }
        ]
      },
      "outcomes": [
        {
          "id": "AP02E010O001",
          "priority": 100,
          "conditions": [
            { "scope": "npc", "target": "P02", "attr": "defense", "op": ">=", "value": 6 },
            { "scope": "npc", "target": "P02", "attr": "speed", "op": ">=", "value": 6 }
          ],
          "text": "白芷推开了铺子门。她从药王谷回来补辅料——考核需要自备辅料，这是暗门槛。她的灵药——品质不差，但数量和年份都不如那些独自闯入核心区的人。组队探索时她分了一株灵药给江枫，自己留的刚好够考核用——没有多余的可以卖。买辅料时她很仔细，每一株都要翻来覆去地看品相。她在铺子里待了很久，比平时任何一次都久。'这些够了。'她把灵石袋放在柜台上，比来时少了不少。考核通过，名次在中游——不够进前几名，但够格拿到藏书阁的通行令牌。权限只限前两层——老档案在最里面那层。白芷不着急——她等得起。丹方残页的抄本被她夹在一本无关的药材图鉴里，放在藏书阁第一层的公共书架上——最安全的地方不是上了锁的暗格，是没人会翻开的地方。",
          "next": [
            { "target": "P02", "nextId": "AP02E011" }
          ]
        },
        {
          "id": "AP02E010O002",
          "priority": 1,
          "conditions": [],
          "text": "白芷推开了铺子门。她来买了几味中品辅料——灵石袋比预想的紧。考核勉强通过——名次垫底。藏书阁通行令牌暂缓发放。她把丹方残页的抄本压在枕头底下——但她多了一个东西：江枫留给她的那张写有配比和火候的丹方。丹方本身不值钱——但它提醒她，自己曾经帮过一个人，而那个人活下来了。这种'帮过忙'的底气和独自成功时的自信不一样——但也是底气。",
          "next": [
            { "target": "P02", "nextId": "AP02E011" }
          ]
        }
      ]
    },
    {
      "id": "AP02E011",
      "type": "personal",
      "title": "白芷·B1线·R13·慢火积累",
      "participants": ["P02"],
      "priority": 10,
      "once": true,
      "trigger": {
        "requirements": [],
        "conditions": [
          { "scope": "world", "attr": "round", "op": ">=", "value": 13 }
        ]
      },
      "outcomes": [
        {
          "id": "AP02E011O001",
          "priority": 100,
          "conditions": [
            { "scope": "npc", "target": "P02", "attr": "defense", "op": ">=", "value": 6 }
          ],
          "text": "白芷来铺子了——买了几颗护体丹和一件最普通不过的防身法宝。不是要进遗迹，是为了在深夜翻档案时不被夜巡弟子发现。她在药王谷的日子比A线更慢——没有玄霜草炼出的上品丹药，谷里的人提起她想不起来她炼过什么特别的。但她没有停。她在药材库里翻了一整年的入库记录——靠帮库房管事发了一年的药材，拿到了在后半夜独自清点库存的差事。在入库记录里找到了二十三年前柳玄清申请辅料的原始单据。赤硝不在清单上。有人事后加了进去——笔迹和丹方残页上的一样。她把原始单据藏在药材库最深处的旧麻袋下面。这不是物证——丹方残页才是物证。但这是佐证——它证明赤硝是'加'进去的，不是原来的配方。",
          "next": [
            { "target": "P02", "nextId": "AP02E012" }
          ]
        },
        {
          "id": "AP02E011O002",
          "priority": 1,
          "conditions": [],
          "text": "白芷来铺子里买了几颗护体丹。深夜翻档案时被夜巡弟子撞见过一次。那个弟子没有告发她——但第二天，库房的旧档案区多了一把新锁。白芷看着那把锁站了一会儿，什么都没说，回去继续炼丹。她在尝试复原二十三年前那张筑基丹方的原始版本——没有赤硝的版本。手指上多了一道烫痕——不是炼失败烫的，是丹炉炸了。",
          "next": [
            { "target": "P02", "nextId": "AP02E012" }
          ]
        }
      ]
    },
    {
      "id": "AP02E012",
      "type": "personal",
      "title": "白芷·B1线·R20·揭发",
      "participants": ["P02"],
      "priority": 10,
      "once": true,
      "trigger": {
        "requirements": [],
        "conditions": [
          { "scope": "world", "attr": "round", "op": ">=", "value": 20 }
        ]
      },
      "outcomes": [
        {
          "id": "AP02E012O001",
          "priority": 100,
          "conditions": [
            { "scope": "npc", "target": "P02", "attr": "defense", "op": ">=", "value": 6 }
          ],
          "text": "灵潮降临，各方势力重组。白芷趁药材大调库期间拿到了丹方残页的原件——佐证完备，时机成熟。天剑宗改革的外部压力让玄清宗不敢压下内部举报。她没有署名——不是怕报复，是不想让这件事变成'一个外门弟子告倒了长老'。赵元恪被传讯的那天，白芷在四人丹房里炼了一炉筑基丹——按照柳玄清原方，不加赤硝。丹成了。师父获救——晚于A线，但赶上了。",
          "next": [
            { "target": "P02", "nextId": "AP02E013" }
          ]
        },
        {
          "id": "AP02E012O002",
          "priority": 50,
          "conditions": [],
          "text": "天剑宗压力推动了调查，但白芷拿到原件时已经晚了。灵潮的混乱窗口太短，柳玄清被搜魂术搜到濒死。他被救出后山时已经不认识任何人了。白芷把丹方残页放在柳玄清床边的桌上——他看了一眼，没有反应。白芷在床边坐了很久。然后她站起来，把残页收好。师父获救，但来晚了。",
          "next": [
            { "target": "P02", "nextId": "AP02E013" }
          ]
        },
        {
          "id": "AP02E012O003",
          "priority": 1,
          "conditions": [],
          "text": "外部压力不存在或不够。白芷在灵潮窗口拿到了原件，但没有渠道递交——天剑宗没有完成改革，玄清宗无人可惧。她把文件袋锁进了自己的丹房暗格——和几年前那页残页一样，等待下一次机会。师父线悬置——物证俱全但无人受理。",
          "next": [
            { "target": "P02", "nextId": "AP02E013" }
          ]
        }
      ]
    },
    {
      "id": "AP02E013",
      "type": "personal",
      "title": "白芷·B1线·R26·终局回访",
      "participants": ["P02"],
      "priority": 10,
      "once": true,
      "trigger": {
        "requirements": [],
        "conditions": [
          { "scope": "world", "attr": "round", "op": ">=", "value": 26 }
        ]
      },
      "outcomes": [
        {
          "id": "AP02E013O001",
          "priority": 100,
          "conditions": [],
          "text": "白芷推开铺子的门。手指比几年前更绿了——不是没洗，是洗不掉了。她把一个布包放在柜台上，里面是一小瓶她自己炼的回气散——标签上工工整整写了配比。还有一包种子——和几年前她在铺子里留的那包一样，但多了几个品种。'掌柜的——我是来跟你说一声。赵元恪的事，我做过。没做完全部——但做了我能做的。种子你留着——以后有人来铺子里买，你就说是一个采药的姑娘留下的。'走到门口时她回过头。南坊的阳光照在柜台上，照着那包种子和刚才放的几颗灵石。'掌柜的——谢谢。还有那个断剑的少年——如果他哪天再来，告诉他欠他的那份灵药，我没忘。'买东西，但没有后续剧情了。",
          "next": [
            { "target": "P02", "nextId": "EVENT_INACTIVE" }
          ]
        }
      ]
    },
    {
      "id": "AP02E014",
      "type": "personal",
      "title": "白芷·B2线·R6·空手回谷",
      "participants": ["P02"],
      "priority": 10,
      "once": true,
      "trigger": {
        "requirements": [],
        "conditions": [
          { "scope": "world", "attr": "round", "op": ">=", "value": 6 }
        ]
      },
      "outcomes": [
        {
          "id": "AP02E014O001",
          "priority": 100,
          "conditions": [],
          "text": "白芷回了药王谷。药篓不重——里面只有几株从遗迹外围勉强采到的低年份灵草，和几件没派上大用场的旧装备。没有考核资格，没有上古灵药，没有任何能让她进入内门视野的东西。但她把袖口那截染血的布条重新扎紧，背好药篓。丹方残页——原件躺在药王谷库房最深处的灰尘里，抄本在她枕头底下。她记得残页上每一个字：每一味药材的药性、柳玄清工整的批注、以及赵元恪用另一种墨水加上的'九转时加三钱赤硝'。她记得——但说不出口。一个连考核都没通过的外门弟子，说内门长老二十三年前害过人？没人会信。",
          "next": [
            { "target": "P02", "nextId": "AP02E015" }
          ]
        }
      ]
    },
    {
      "id": "AP02E015",
      "type": "personal",
      "title": "白芷·B2线·R10·基础补给",
      "participants": ["P02"],
      "priority": 10,
      "once": true,
      "trigger": {
        "requirements": [],
        "conditions": [
          { "scope": "world", "attr": "round", "op": ">=", "value": 10 }
        ]
      },
      "outcomes": [
        {
          "id": "AP02E015O001",
          "priority": 100,
          "conditions": [],
          "text": "白芷来过铺子一次——买了最便宜的辟谷丹和几包扎伤口的纱布。灵石不多——考核没参加，外派补贴降回了基础标准。买东西时她没有像以前那样挑剔品相——不是不挑了，是灵石不够挑。'掌柜的——上次你卖给我的装备是真的好。是我自己运气不够。'她把灵石袋在手里攥了攥，放下一小堆零碎的灵石，'这些——够吗？'她没有抱怨，也没有诉苦。只是把东西收好，鞠了一躬，背好药篓走了。",
          "next": [
            { "target": "P02", "nextId": "AP02E016" }
          ]
        }
      ]
    },
    {
      "id": "AP02E016",
      "type": "personal",
      "title": "白芷·B2线·漫长等待",
      "participants": ["P02"],
      "priority": 10,
      "once": true,
      "trigger": {
        "requirements": [],
        "conditions": [
          { "scope": "world", "attr": "round", "op": ">=", "value": 15 }
        ]
      },
      "outcomes": [
        {
          "id": "AP02E016O001",
          "priority": 100,
          "conditions": [],
          "text": "白芷在药王谷的日子是安静的。没有考核，没有独立的丹房，没有通往内门的路径。她和其他三个外门弟子共用一间丹房，每天做最基础的药材分拣和丹炉看火。手指上的绿色越来越深，袖口上的焦洞越来越多。但她的眼神没有变——不是那种'咬着牙要翻身'的狠劲，是一种更慢的东西：等。她在药王谷的药材库里翻了一年半的入库记录——没有通行令牌，靠的是帮库房管事搬了大半年的麻袋。她把看到的东西记在脑子里，一个字一个字地背。和丹方残页一样。她不需要别的——她需要一个外部推力。那座叫天剑宗的山门里，有一个同样在跟体制较劲的断剑少年。",
          "next": [
            { "target": "P02", "nextId": "AP02E017" }
          ]
        }
      ]
    },
    {
      "id": "AP02E017",
      "type": "personal",
      "title": "白芷·B2线·R20·最后时机",
      "participants": ["P02"],
      "priority": 10,
      "once": true,
      "trigger": {
        "requirements": [],
        "conditions": [
          { "scope": "world", "attr": "round", "op": ">=", "value": 20 }
        ]
      },
      "outcomes": [
        {
          "id": "AP02E017O001",
          "priority": 100,
          "conditions": [
            { "scope": "npc", "target": "P02", "attr": "defense", "op": ">=", "value": 5 },
            { "scope": "npc", "target": "P02", "attr": "speed", "op": ">=", "value": 5 }
          ],
          "text": "灵潮降临，各方势力重组。药王谷在混乱中出现几个微小裂口——库存大调库时旧档案区的门没锁；内门长老被派往各地坐镇，赵元恪不在谷里；退居二线的老丹师在整理旧档时翻到了柳玄清一份未被销毁的原始日志。白芷趁档案区门没锁的那一晚，溜进了最深处的库房。她找到了丹方残页的原件——还在她两年前放回去的地方。她把原件揣进袖子里，又翻出了柳玄清的原始辅料申请单。走出库房时天刚亮——她把两样东西放在老丹师的桌面上。老丹师看了一眼，什么都没说。而天剑宗改革的风声已经传到了玄清宗——长老会面对外部压力，不敢压住内部举报。三天后，执法堂传讯赵元恪。师父获救——最远的路，最晚的抵达。",
          "next": [
            { "target": "P02", "nextId": "AP02E018" }
          ]
        },
        {
          "id": "AP02E017O002",
          "priority": 1,
          "conditions": [],
          "text": "灵潮降临，白芷错过了最后的窗口。赵元恪从外地回来后，档案区换了新锁——不是普通锁，是加了阵法的锁。白芷看着那把锁站了很久。然后她转身回了四人丹房，把枕头底下的抄本翻出来看了一遍。她不会忘记上面写了什么——但她能做的事，到这里为止了。师父线悬置——证人活着但无力开口，物证石沉大海。但丹方残页还在——会一直等。",
          "next": [
            { "target": "P02", "nextId": "AP02E018" }
          ]
        }
      ]
    },
    {
      "id": "AP02E018",
      "type": "personal",
      "title": "白芷·B2线·R26·终局回访",
      "participants": ["P02"],
      "priority": 10,
      "once": true,
      "trigger": {
        "requirements": [],
        "conditions": [
          { "scope": "world", "attr": "round", "op": ">=", "value": 26 }
        ]
      },
      "outcomes": [
        {
          "id": "AP02E018O001",
          "priority": 100,
          "conditions": [],
          "text": "白芷推开铺子的门。她已经不是当年那个手指发绿的少女了——手指还是绿的，但眼角多了细纹。她在药王谷待了够久，久到新来的弟子以为她从来就是谷里的人。'掌柜的——你还记得我吗。那个在林子里采药采不到的，遗迹里被禁制划破袖子的。'她把一个布包放在柜台上。不像A线那样满满一盒亲手炼的丹药，也不像B-1线那样有种子。只是一个布包——里面有一页纸。不是丹方残页的抄本，是白芷自己写的——她把二十三年前那件事从头到尾写了下来：柳玄清是谁，赵元恪做了什么，丹方上那行字是什么意思，原件锁在药王谷库房哪个柜子里。最后一句话是：'如果有人拿着这页纸来找你——说明我已经不能说话了。请你把这个交给信得过的人。'她把布包推过去。'掌柜的——我知道你不会看。但万一有那一天……你替我收着。'走到门口时她回过头。南坊的阳光还是和几年前一样——照在石板路上亮晃晃的。'谢谢你这间铺子。'买东西，但没有后续剧情了。",
          "next": [
            { "target": "P02", "nextId": "EVENT_INACTIVE" }
          ]
        }
      ]
    },
    {
      "id": "AP02E019",
      "type": "personal",
      "title": "白芷·B2触发·等待组队",
      "participants": ["P02"],
      "priority": 10,
      "once": true,
      "trigger": {
        "requirements": [],
        "conditions": [
          { "scope": "world", "attr": "round", "op": ">=", "value": 8 }
        ]
      },
      "outcomes": [
        {
          "id": "AP02E019O001",
          "priority": 100,
          "conditions": [],
          "text": "白芷在铺子门口站了一会儿。她问了一圈——没有合适的剑修能一起进遗迹。江枫已经独自进过了，或者已经不在了。她看着南坊的石板路，阳光很好，照得路面上亮晃晃的。她把袖口那截染血的布条重新扎紧，背好药篓。'没事。我自己再想想办法。'她往落仙城城门的方向走去——回了药王谷。药篓空空，但丹方残页还在脑子里。",
          "next": [
            { "target": "P02", "nextId": "AP02E014" }
          ]
        }
      ]
    }
  ]
}
